wonderfull/__init__.py
wonderfull/abstractions/__init__.py
wonderfull/abstractions/agents.py
wonderfull/abstractions/envs.py
wonderfull/agents/__init__.py
wonderfull/envs/__init__.py
wonderfull/envs/implementations/__init__.py
wonderfull/envs/implementations/sequential.py
wonderfull/memories/__init__.py
wonderfull/trainers.py
wonderfull/utils/__init__.py
wonderfull-0.0.0.dist-info/LICENSE.md
wonderfull-0.0.0.dist-info/METADATA
wonderfull-0.0.0.dist-info/WHEEL
wonderfull-0.0.0.dist-info/RECORD
