Metadata-Version: 2.1
Name: wonderfull
Version: 0.0.0
Summary: The complete framework for interactive learning.
License: Apache
Author: RenChu Wang
Author-email: patrick1031wang@gmail.com
Requires-Python: >=3.10,<3.11
Classifier: License :: Other/Proprietary License
Classifier: Programming Language :: Python :: 3
Classifier: Programming Language :: Python :: 3.10
Requires-Dist: aim (>=3.17.5,<4.0.0)
Requires-Dist: dm-reverb (>=0.11.0,<0.12.0)
Requires-Dist: gymnasium (>=0.28.1,<0.29.0)
Requires-Dist: hydra-core (>=1.3.2,<2.0.0)
Requires-Dist: omegaconf (>=2.3.0,<3.0.0)
Requires-Dist: pettingzoo (>=1.23.1,<2.0.0)
Requires-Dist: ray (>=2.5.0,<3.0.0)
Requires-Dist: rich (>=13.4.2,<14.0.0)
Requires-Dist: tensordict (>=0.1.2,<0.2.0)
Requires-Dist: torch (>=2.0.0,<3.0.0)
Requires-Dist: torchrl (>=0.1.1,<0.2.0)
